AUTHORS.rst
CONTRIBUTING.rst
MANIFEST.in
README.rst
setup.cfg
setup.py
docs/Makefile
docs/authors.rst
docs/case118.rst
docs/case24-ieee-rts.rst
docs/case5.rst
docs/conf.py
docs/contributing.rst
docs/history.rst
docs/index.rst
docs/installation.rst
docs/make.bat
docs/readme.rst
docs/testcases.rst
docs/usage.rst
psst/__init__.py
psst/cli.py
psst/psst.py
psst/utils.py
psst.egg-info/PKG-INFO
psst.egg-info/SOURCES.txt
psst.egg-info/dependency_links.txt
psst.egg-info/entry_points.txt
psst.egg-info/not-zip-safe
psst.egg-info/requires.txt
psst.egg-info/top_level.txt
psst/case/__init__.py
psst/case/blank.m
psst/case/descriptors.py
psst/case/utils.py
psst/case/matpower/__init__.py
psst/case/matpower/case_parser.py
psst/case/matpower/reader.py
psst/case/matpower/utils.py
psst/model/__init__.py
psst/model/constraints.py
psst/model/demand.py
psst/model/generators.py
psst/model/model.py
psst/model/network.py
psst/model/price_sensitive_load.py
psst/model/reserves.py
psst/model/storage.py
psst/network/__init__.py
psst/plot/__init__.py
psst/plot/network.py
psst/plot/plot.py
psst/plot/plotmpld3.py
psst/solver/__init__.py
psst/solver/results.py
tests/__init__.py
tests/test_PSL_3Bus.py
tests/test_PSLoad.py
tests/test_psst.py