Metadata-Version: 2.1
Name: psst
Version: 0.1.9
Summary: Power System Simulation Toolbox
Home-page: https://github.com/power-system-simulation-toolbox/psst
Author: Dheepak Krishnamurthy
Author-email: kdheepak89@gmail.com
License: MIT license
Keywords: psst
Platform: UNKNOWN
Classifier: Development Status :: 4 - Beta
Classifier: Intended Audience :: Developers
Classifier: License :: OSI Approved :: MIT License
Classifier: Natural Language :: English
Classifier: Programming Language :: Python :: 3
Classifier: Programming Language :: Python :: 3.3
Classifier: Programming Language :: Python :: 3.4
Classifier: Programming Language :: Python :: 3.5
